ALIOCrawler-1.0.2.dist-info/RECORD
ALIOCrawler-1.0.2.dist-info/metadata.json
ALIOCrawler-1.0.2.dist-info/WHEEL
ALIOCrawler-1.0.2.dist-info/entry_points.txt
ALIOCrawler-1.0.2.dist-info/DESCRIPTION.rst
ALIOCrawler-1.0.2.dist-info/top_level.txt
ALIOCrawler-1.0.2.dist-info/METADATA
ALIOCrawler/__init__.py
ALIOCrawler/ALIOCrawler.py
ALIOCrawler/__main__.py
